README.rst
setup.py
metalpipe/__init__.py
metalpipe/metalpipe_recorder.py
metalpipe/node.py
metalpipe.egg-info/PKG-INFO
metalpipe.egg-info/SOURCES.txt
metalpipe.egg-info/dependency_links.txt
metalpipe.egg-info/requires.txt
metalpipe.egg-info/top_level.txt
metalpipe/bin/metalpipe
metalpipe/exp/__init__.py
metalpipe/exp/import_hook.py
metalpipe/exp/nanostream_encoder.py
metalpipe/exp/nanostream_file_handler.py
metalpipe/exp/nanostream_inner_join.py
metalpipe/exp/nanostream_json_validator.py
metalpipe/message/__init__.py
metalpipe/message/batch.py
metalpipe/message/canary.py
metalpipe/message/message.py
metalpipe/message/trigger.py
metalpipe/node_classes/__init__.py
metalpipe/node_classes/civis_nodes.py
metalpipe/node_classes/network_nodes.py
metalpipe/node_classes/table_nodes.py
metalpipe/node_queue/__init__.py
metalpipe/node_queue/queue.py
metalpipe/utils/__init__.py
metalpipe/utils/data_structures.py
metalpipe/utils/helpers.py
metalpipe/utils/required_arguments.py
metalpipe/utils/set_attributes.py
metalpipe/utils/treehorn.py
metalpipe/watchdog/__init__.py
metalpipe/watchdog/watchdog.py