Metadata-Version: 1.1
Name: metalpipe
Version: 0.1.15
Summary: Modules for ETL Pipelines
Home-page: https://github.com/zacernst/metalpipe
Author: Zachary Ernst
Author-email: zac.ernst@gmail.com
License: UNKNOWN
Platform: UNKNOWN
Classifier: Programming Language :: Python :: 3
Classifier: License :: OSI Approved :: MIT License
Classifier: Operating System :: OS Independent
